discord_logger/__init__.py
discord_logger/message_logger.py
discord_logger/utils.py
examples/__init__.py
examples/basic_message.py
examples/basic_message_without_hostname.py
examples/complete_error_traceback.py
examples/error_message.py
examples/success_message.py
discord_logger_ng-1.2.4.dist-info/LICENSE
discord_logger_ng-1.2.4.dist-info/METADATA
discord_logger_ng-1.2.4.dist-info/WHEEL
discord_logger_ng-1.2.4.dist-info/top_level.txt
discord_logger_ng-1.2.4.dist-info/RECORD
