Metadata-Version: 2.1
Name: discord-logger-ng
Version: 1.2.4
Summary: Discord Logger is a custom message logger to Discord for Python 3 with proxy and user / role mentions support.
Home-page: https://github.com/iamtalhaasghar/python-discord-logger
Author: Talha Asghar
License: MIT License
Keywords: monitoring,discord,messaging,logging,health-check,notification-service,notification,discord-webhook
Classifier: Environment :: Web Environment
Classifier: Intended Audience :: Developers
Classifier: License :: OSI Approved :: MIT License
Classifier: Operating System :: OS Independent
Classifier: Programming Language :: Python :: 3.5
Classifier: Programming Language :: Python :: 3.6
Classifier: Programming Language :: Python :: 3.7
Classifier: Topic :: Internet :: WWW/HTTP
Classifier: Topic :: Internet :: WWW/HTTP :: Dynamic Content
Requires-Python: >=3.5
License-File: LICENSE
Requires-Dist: discord-webhook ==0.13.0
Requires-Dist: pyyaml ==5.4.1
